pynance/__init__.py
pynance/chart.py
pynance/common.py
pynance/dateutils.py
pynance/interest.py
pynance/pf.py
pynance/data/__init__.py
pynance/data/combine.py
pynance/data/compare.py
pynance/data/feat.py
pynance/data/lab.py
pynance/data/prep.py
pynance/data/retrieve.py
pynance/learn/__init__.py
pynance/learn/linreg.py
pynance/learn/metrics.py
pynance/tech/__init__.py
pynance/tech/movave.py
pynance/tech/simple.py
pynance/tst/__init__.py
pynance/tst/integ/__init__.py
pynance/tst/integ/data/__init__.py
pynance/tst/integ/data/test_retrieve.py
pynance/tst/unit/__init__.py
pynance/tst/unit/test_common.py
pynance/tst/unit/test_dateutils.py
pynance/tst/unit/test_interest.py
pynance/tst/unit/test_pf.py
pynance/tst/unit/data/__init__.py
pynance/tst/unit/data/test_combine.py
pynance/tst/unit/data/test_compare.py
pynance/tst/unit/data/test_feat.py
pynance/tst/unit/data/test_lab.py
pynance/tst/unit/data/test_preprocess.py
pynance/tst/unit/learn/__init__.py
pynance/tst/unit/learn/test_linreg.py
pynance/tst/unit/learn/test_metrics.py
pynance/tst/unit/tech/__init__.py
pynance/tst/unit/tech/test_movave.py
pynance/tst/unit/tech/test_simple.py
pynance-1.0.0.dist-info/LICENSE
pynance-1.0.0.dist-info/METADATA
pynance-1.0.0.dist-info/WHEEL
pynance-1.0.0.dist-info/top_level.txt
pynance-1.0.0.dist-info/RECORD
