Metadata-Version: 1.1
Name: pynance
Version: 1.0.0
Summary: Retrieve and analyze financial market data
Home-page: https://github.com/GriffinAustin/pynance
Author: Griffin Austin
Author-email: griffinaustin@protonmail.com
License: UNKNOWN
Download-URL: https://github.com/GriffinAustin/pynance/tarball/1.0.0
Keywords: finance investment stocks equities market options derivatives
Platform: UNKNOWN
Classifier: Development Status :: 5 - Production/Stable
Classifier: Intended Audience :: Financial and Insurance Industry
Classifier: Intended Audience :: Developers
Classifier: License :: OSI Approved
Classifier: License :: OSI Approved :: MIT License
Classifier: Programming Language :: Python
Classifier: Programming Language :: Python :: 3
Classifier: Operating System :: Microsoft :: Windows
Classifier: Operating System :: POSIX
Classifier: Operating System :: Unix
Classifier: Operating System :: MacOS
Classifier: Topic :: Office/Business
Classifier: Topic :: Office/Business :: Financial
Classifier: Topic :: Office/Business :: Financial :: Investment
